topalias/__init__.py
topalias/__main__.py
topalias/aliascore.py
topalias/cli copy 2.py
topalias/cli copy Hamachi.py
topalias/cli.py
topalias/cli2.py
topalias/cli310.py
topalias/cli313.py
topalias/exp.py
topalias/statistic.py
topalias-4.3.1.dist-info/licenses/LICENSE
topalias-4.3.1.dist-info/METADATA
topalias-4.3.1.dist-info/WHEEL
topalias-4.3.1.dist-info/entry_points.txt
topalias-4.3.1.dist-info/top_level.txt
topalias-4.3.1.dist-info/RECORD
